endaq/cloud/API_wrapper.py
endaq/cloud/__init__.py
endaq/cloud/core.py
endaq_cloud-1.1.0.dist-info/LICENSE
endaq_cloud-1.1.0.dist-info/METADATA
endaq_cloud-1.1.0.dist-info/WHEEL
endaq_cloud-1.1.0.dist-info/entry_points.txt
endaq_cloud-1.1.0.dist-info/top_level.txt
endaq_cloud-1.1.0.dist-info/RECORD
