Metadata-Version: 2.1
Name: endaq-cloud
Version: 1.1.0
Summary: The cloud subpackage for endaq-python
Home-page: https://github.com/MideTechnology/endaq-python-cloud
Author: Mide Technology
Author-email: help@mide.com
License: MIT
Keywords: ebml binary ide mide endaq
Platform: UNKNOWN
Classifier: Development Status :: 4 - Beta
Classifier: License :: OSI Approved :: MIT License
Classifier: Natural Language :: English
Classifier: Programming Language :: Python :: 3.5
Classifier: Programming Language :: Python :: 3.6
Classifier: Programming Language :: Python :: 3.7
Classifier: Programming Language :: Python :: 3.8
Classifier: Programming Language :: Python :: 3.9
Classifier: Topic :: Scientific/Engineering
License-File: LICENSE
Requires-Dist: requests
Requires-Dist: python-dotenv
Provides-Extra: example
Requires-Dist: requests ; extra == 'example'
Requires-Dist: python-dotenv ; extra == 'example'
Provides-Extra: test
Requires-Dist: requests ; extra == 'test'
Requires-Dist: python-dotenv ; extra == 'test'
